pythonsite/__init__.py
pythonsite/elements.py
pythonsite-0.0.3.dist-info/LICENSE
pythonsite-0.0.3.dist-info/METADATA
pythonsite-0.0.3.dist-info/WHEEL
pythonsite-0.0.3.dist-info/top_level.txt
pythonsite-0.0.3.dist-info/RECORD
